{"version":"1.0.0","tokens":"941a11660f3736aed07c48f6d809a8ccf1b150df7626d5ad24bc6464b66022ad","appConfigSchema":{"properties":"","default":""},"appConfig":{"$chakraConfig":{"extendTheme":{"semanticTokens":{"colors":{"chakra-body-text":{"_light":"gray.800","_dark":"whiteAlpha.900"},"chakra-body-bg":{"_light":"white","_dark":"gray.800"},"chakra-border-color":{"_light":"gray.200","_dark":"whiteAlpha.300"},"chakra-inverse-text":{"_light":"white","_dark":"gray.800"},"chakra-subtle-bg":{"_light":"gray.100","_dark":"gray.700"},"chakra-subtle-text":{"_light":"gray.600","_dark":"gray.400"},"chakra-placeholder-color":{"_light":"gray.500","_dark":"whiteAlpha.400"},"bodyBg":{"default":"white","_dark":"#0e0f15"},"pageBackgroundGradiant":"radial-gradient(circle at 10% 45%,rgba(149,176,241,0), rgba(149,176,241,0) 50%),radial-gradient(circle at 82% 26%,rgba(43,199,119,0.05), rgba(43,199,119,0) 50%),radial-gradient(circle at 11% 15%,rgba(149,0,255,0.06), rgba(149,0,255,0) 50%),radial-gradient(circle at 27% 54%,rgba(86,210,146,0.06), rgba(86,210,146,0) 30%),radial-gradient(circle at 67% 70%,rgba(101,0,255,0.05), rgba(101,0,255,0) 10%)","bodyText":{"default":"gray.700","_dark":"whiteAlpha.900"},"_bodyBg":{"default":"white","_dark":"gray.900"},"subtitleText":{"default":"gray.500","_dark":"whiteAlpha.600"},"pillNoticeBg":{"default":"emerald.50","_dark":"rgba(41, 236, 139, 0.14)"},"pillNoticeText":{"default":"#226044","_dark":"rgb(170, 255, 213)"},"featuresBorderColor":{"default":"#19b971","_dark":"rgba(41, 236, 139, 0.5)"},"featuresBorderColorHover":{"default":"#19b971","_dark":"rgba(41, 236, 139, 0.7)"},"featuresTextColor":{"default":"rgba(41, 236, 139, 0.1)","_dark":"rgba(41, 236, 139, 0.2)"},"featuresTextColorHover":{"default":"rgba(41, 236, 139, 0.2)","_dark":"rgba(41, 236, 139, 0.3)"}}},"direction":"ltr","breakpoints":{"base":"0em","sm":"30em","md":"48em","lg":"62em","xl":"80em","2xl":"96em"},"zIndices":{"hide":-1,"auto":"auto","base":0,"docked":10,"dropdown":1000,"sticky":1100,"banner":1200,"overlay":1300,"modal":1400,"popover":1500,"skipLink":1600,"toast":1700,"tooltip":1800},"radii":{"none":"0","sm":"0.125rem","base":"0.25rem","md":"0.375rem","lg":"0.5rem","xl":"0.75rem","2xl":"1rem","3xl":"1.5rem","full":"9999px"},"blur":{"none":0,"sm":"4px","base":"8px","md":"12px","lg":"16px","xl":"24px","2xl":"40px","3xl":"64px"},"colors":{"transparent":"transparent","current":"currentColor","black":"#000000","white":"#FFFFFF","whiteAlpha":{"50":"rgba(255, 255, 255, 0.04)","100":"rgba(255, 255, 255, 0.06)","200":"rgba(255, 255, 255, 0.08)","300":"rgba(255, 255, 255, 0.16)","400":"rgba(255, 255, 255, 0.24)","500":"rgba(255, 255, 255, 0.36)","600":"rgba(255, 255, 255, 0.48)","700":"rgba(255, 255, 255, 0.64)","800":"rgba(255, 255, 255, 0.80)","900":"rgba(255, 255, 255, 0.92)"},"blackAlpha":{"50":"rgba(0, 0, 0, 0.04)","100":"rgba(0, 0, 0, 0.06)","200":"rgba(0, 0, 0, 0.08)","300":"rgba(0, 0, 0, 0.16)","400":"rgba(0, 0, 0, 0.24)","500":"rgba(0, 0, 0, 0.36)","600":"rgba(0, 0, 0, 0.48)","700":"rgba(0, 0, 0, 0.64)","800":"rgba(0, 0, 0, 0.80)","900":"rgba(0, 0, 0, 0.92)"},"gray":{"50":"#F7FAFC","100":"#EDF2F7","200":"#E2E8F0","300":"#CBD5E0","400":"#A0AEC0","500":"#718096","600":"#4A5568","700":"#2D3748","800":"#1A202C","900":"#171923"},"red":{"50":"#FFF5F5","100":"#FED7D7","200":"#FEB2B2","300":"#FC8181","400":"#F56565","500":"#E53E3E","600":"#C53030","700":"#9B2C2C","800":"#822727","900":"#63171B"},"orange":{"50":"#FFFAF0","100":"#FEEBC8","200":"#FBD38D","300":"#F6AD55","400":"#ED8936","500":"#DD6B20","600":"#C05621","700":"#9C4221","800":"#7B341E","900":"#652B19"},"yellow":{"50":"#FFFFF0","100":"#FEFCBF","200":"#FAF089","300":"#F6E05E","400":"#ECC94B","500":"#D69E2E","600":"#B7791F","700":"#975A16","800":"#744210","900":"#5F370E"},"green":{"50":"#F0FFF4","100":"#C6F6D5","200":"#9AE6B4","300":"#68D391","400":"#48BB78","500":"#38A169","600":"#2F855A","700":"#276749","800":"#22543D","900":"#1C4532"},"teal":{"50":"#E6FFFA","100":"#B2F5EA","200":"#81E6D9","300":"#4FD1C5","400":"#38B2AC","500":"#319795","600":"#2C7A7B","700":"#285E61","800":"#234E52","900":"#1D4044"},"blue":{"50":"#ebf8ff","100":"#bee3f8","200":"#90cdf4","300":"#63b3ed","400":"#4299e1","500":"#3182ce","600":"#2b6cb0","700":"#2c5282","800":"#2a4365","900":"#1A365D"},"cyan":{"50":"#EDFDFD","100":"#C4F1F9","200":"#9DECF9","300":"#76E4F7","400":"#0BC5EA","500":"#00B5D8","600":"#00A3C4","700":"#0987A0","800":"#086F83","900":"#065666"},"purple":{"50":"#FAF5FF","100":"#E9D8FD","200":"#D6BCFA","300":"#B794F4","400":"#9F7AEA","500":"#805AD5","600":"#6B46C1","700":"#553C9A","800":"#44337A","900":"#322659"},"pink":{"50":"#FFF5F7","100":"#FED7E2","200":"#FBB6CE","300":"#F687B3","400":"#ED64A6","500":"#D53F8C","600":"#B83280","700":"#97266D","800":"#702459","900":"#521B41"},"linkedin":{"50":"#E8F4F9","100":"#CFEDFB","200":"#9BDAF3","300":"#68C7EC","400":"#34B3E4","500":"#00A0DC","600":"#008CC9","700":"#0077B5","800":"#005E93","900":"#004471"},"facebook":{"50":"#E8F4F9","100":"#D9DEE9","200":"#B7C2DA","300":"#6482C0","400":"#4267B2","500":"#385898","600":"#314E89","700":"#29487D","800":"#223B67","900":"#1E355B"},"messenger":{"50":"#D0E6FF","100":"#B9DAFF","200":"#A2CDFF","300":"#7AB8FF","400":"#2E90FF","500":"#0078FF","600":"#0063D1","700":"#0052AC","800":"#003C7E","900":"#002C5C"},"whatsapp":{"50":"#dffeec","100":"#b9f5d0","200":"#90edb3","300":"#65e495","400":"#3cdd78","500":"#22c35e","600":"#179848","700":"#0c6c33","800":"#01421c","900":"#001803"},"twitter":{"50":"#E5F4FD","100":"#C8E9FB","200":"#A8DCFA","300":"#83CDF7","400":"#57BBF5","500":"#1DA1F2","600":"#1A94DA","700":"#1681BF","800":"#136B9E","900":"#0D4D71"},"telegram":{"50":"#E3F2F9","100":"#C5E4F3","200":"#A2D4EC","300":"#7AC1E4","400":"#47A9DA","500":"#0088CC","600":"#007AB8","700":"#006BA1","800":"#005885","900":"#003F5E"},"emerald":{"50":"#B6E5D0","100":"#A3DEC4","200":"#7ED0AB","300":"#58C393","400":"#3EAA7A","500":"#30855F","600":"#226044","700":"#153A29","800":"#07150F","900":"#000000","DEFAULT":"#30855F","default":"#30855F"},"discord":{"primary":"#7289DA","accessible":"#5570D2"}},"letterSpacings":{"tighter":"-0.05em","tight":"-0.025em","normal":"0","wide":"0.025em","wider":"0.05em","widest":"0.1em"},"lineHeights":{"3":".75rem","4":"1rem","5":"1.25rem","6":"1.5rem","7":"1.75rem","8":"2rem","9":"2.25rem","10":"2.5rem","normal":"normal","none":1,"shorter":1.25,"short":1.375,"base":1.5,"tall":1.625,"taller":"2"},"fontWeights":{"hairline":100,"thin":200,"light":300,"normal":400,"medium":500,"semibold":600,"bold":700,"extrabold":800,"black":900},"fonts":{"heading":"DM Sans, -apple-system, BlinkMacSystemFont, \"Segoe UI\", Helvetica, Arial, sans-serif, \"Apple Color Emoji\", \"Segoe UI Emoji\", \"Segoe UI Symbol\"","body":"DM Sans, -apple-system, BlinkMacSystemFont, \"Segoe UI\", Helvetica, Arial, sans-serif, \"Apple Color Emoji\", \"Segoe UI Emoji\", \"Segoe UI Symbol\"","mono":"IBM Plex Mono"},"fontSizes":{"3xs":"0.45rem","2xs":"0.625rem","xs":"0.75rem","sm":"0.875rem","md":"1rem","lg":"1.125rem","xl":"1.25rem","2xl":"1.5rem","3xl":"1.875rem","4xl":"2.25rem","5xl":"3rem","6xl":"3.75rem","7xl":"4.5rem","8xl":"6rem","9xl":"8rem"},"sizes":{"1":"0.25rem","2":"0.5rem","3":"0.75rem","4":"1rem","5":"1.25rem","6":"1.5rem","7":"1.75rem","8":"2rem","9":"2.25rem","10":"2.5rem","12":"3rem","14":"3.5rem","16":"4rem","20":"5rem","24":"6rem","28":"7rem","32":"8rem","36":"9rem","40":"10rem","44":"11rem","48":"12rem","52":"13rem","56":"14rem","60":"15rem","64":"16rem","72":"18rem","80":"20rem","96":"24rem","px":"1px","0.5":"0.125rem","1.5":"0.375rem","2.5":"0.625rem","3.5":"0.875rem","max":"max-content","min":"min-content","full":"100%","3xs":"14rem","2xs":"16rem","xs":"20rem","sm":"24rem","md":"28rem","lg":"32rem","xl":"36rem","2xl":"42rem","3xl":"48rem","4xl":"56rem","5xl":"64rem","6xl":"72rem","7xl":"80rem","8xl":"90rem","prose":"60ch","container":{"sm":"640px","md":"768px","lg":"1024px","xl":"1280px"}},"shadows":{"xs":"0 0 0 1px rgba(0, 0, 0, 0.05)","sm":"0 1px 2px 0 rgba(0, 0, 0, 0.05)","base":"0 1px 3px 0 rgba(0, 0, 0, 0.1), 0 1px 2px 0 rgba(0, 0, 0, 0.06)","md":"0 4px 6px -1px rgba(0, 0, 0, 0.1), 0 2px 4px -1px rgba(0, 0, 0, 0.06)","lg":"0 10px 15px -3px rgba(0, 0, 0, 0.1), 0 4px 6px -2px rgba(0, 0, 0, 0.05)","xl":"0 20px 25px -5px rgba(0, 0, 0, 0.1), 0 10px 10px -5px rgba(0, 0, 0, 0.04)","2xl":"0 25px 50px -12px rgba(0, 0, 0, 0.25)","outline":"0 0 0 4px rgba(47, 133, 90, 0.62)","inner":"inset 0 2px 4px 0 rgba(0,0,0,0.06)","none":"none","dark-lg":"rgba(0, 0, 0, 0.1) 0px 0px 0px 1px, rgba(0, 0, 0, 0.2) 0px 5px 10px, rgba(0, 0, 0, 0.4) 0px 15px 40px","search":"0 0 0 1px rgba(16,22,26,.1), 0 4px 8px rgba(16,22,26,.2), 0 18px 46px 6px rgba(16,22,26,.2)"},"space":{"1":"0.25rem","2":"0.5rem","3":"0.75rem","4":"1rem","5":"1.25rem","6":"1.5rem","7":"1.75rem","8":"2rem","9":"2.25rem","10":"2.5rem","12":"3rem","14":"3.5rem","16":"4rem","20":"5rem","24":"6rem","28":"7rem","32":"8rem","36":"9rem","40":"10rem","44":"11rem","48":"12rem","52":"13rem","56":"14rem","60":"15rem","64":"16rem","72":"18rem","80":"20rem","96":"24rem","px":"1px","0.5":"0.125rem","1.5":"0.375rem","2.5":"0.625rem","3.5":"0.875rem"},"borders":{"none":0,"1px":"1px solid","2px":"2px solid","4px":"4px solid","8px":"8px solid"},"transition":{"property":{"common":"background-color, border-color, color, fill, stroke, opacity, box-shadow, transform","colors":"background-color, border-color, color, fill, stroke","dimensions":"width, height","position":"left, right, top, bottom","background":"background-color, background-image, background-position"},"easing":{"ease-in":"cubic-bezier(0.4, 0, 1, 1)","ease-out":"cubic-bezier(0, 0, 0.2, 1)","ease-in-out":"cubic-bezier(0.4, 0, 0.2, 1)"},"duration":{"ultra-fast":"50ms","faster":"100ms","fast":"150ms","normal":"200ms","slow":"300ms","slower":"400ms","ultra-slow":"500ms"}},"components":{"Accordion":{"parts":["root","container","button","panel","icon"],"baseStyle":{"container":{"borderTopWidth":"1px","borderColor":"inherit","_last":{"borderBottomWidth":"1px"}},"button":{"transitionProperty":"common","transitionDuration":"normal","fontSize":"md","_focusVisible":{"boxShadow":"outline"},"_hover":{"bg":"blackAlpha.50"},"_disabled":{"opacity":0.4,"cursor":"not-allowed"},"px":"4","py":"2"},"panel":{"pt":"2","px":"4","pb":"5"},"icon":{"fontSize":"1.25em"}}},"Alert":{"parts":["title","description","container","icon","spinner"],"baseStyle":{"container":{"bg":"var(--alert-bg)","px":"4","py":"3"},"title":{"fontWeight":"bold","lineHeight":"6","marginEnd":"2"},"description":{"lineHeight":"6"},"icon":{"color":"var(--alert-fg)","flexShrink":0,"marginEnd":"3","w":"5","h":"6"},"spinner":{"color":"var(--alert-fg)","flexShrink":0,"marginEnd":"3","w":"5","h":"5"}},"variants":{},"defaultProps":{"variant":"subtle","colorScheme":"blue"}},"Avatar":{"parts":["label","badge","container","excessLabel","group"],"sizes":{"2xs":{"container":{"width":4,"height":4,"fontSize":"calc(1rem / 2.5)"},"excessLabel":{"width":4,"height":4},"label":{"fontSize":"calc(1rem / 2.5)","lineHeight":"1rem"}},"xs":{"container":{"width":6,"height":6,"fontSize":"calc(1.5rem / 2.5)"},"excessLabel":{"width":6,"height":6},"label":{"fontSize":"calc(1.5rem / 2.5)","lineHeight":"1.5rem"}},"sm":{"container":{"width":8,"height":8,"fontSize":"calc(2rem / 2.5)"},"excessLabel":{"width":8,"height":8},"label":{"fontSize":"calc(2rem / 2.5)","lineHeight":"2rem"}},"md":{"container":{"width":12,"height":12,"fontSize":"calc(3rem / 2.5)"},"excessLabel":{"width":12,"height":12},"label":{"fontSize":"calc(3rem / 2.5)","lineHeight":"3rem"}},"lg":{"container":{"width":16,"height":16,"fontSize":"calc(4rem / 2.5)"},"excessLabel":{"width":16,"height":16},"label":{"fontSize":"calc(4rem / 2.5)","lineHeight":"4rem"}},"xl":{"container":{"width":24,"height":24,"fontSize":"calc(6rem / 2.5)"},"excessLabel":{"width":24,"height":24},"label":{"fontSize":"calc(6rem / 2.5)","lineHeight":"6rem"}},"2xl":{"container":{"width":32,"height":32,"fontSize":"calc(8rem / 2.5)"},"excessLabel":{"width":32,"height":32},"label":{"fontSize":"calc(8rem / 2.5)","lineHeight":"8rem"}},"full":{"container":{"width":"100%","height":"100%","fontSize":"calc(100% / 2.5)"},"excessLabel":{"width":"100%","height":"100%"},"label":{"fontSize":"calc(100% / 2.5)"}}},"defaultProps":{"size":"md"}},"Badge":{"baseStyle":{"px":1,"textTransform":"uppercase","fontSize":"xs","borderRadius":"sm","fontWeight":"bold","bg":"var(--badge-bg)","color":"var(--badge-color)","boxShadow":"var(--badge-shadow)"},"variants":{},"defaultProps":{"variant":"subtle","colorScheme":"gray"}},"Breadcrumb":{"parts":["link","item","container","separator"],"baseStyle":{"link":{"transitionProperty":"common","transitionDuration":"fast","transitionTimingFunction":"ease-out","outline":"none","color":"inherit","textDecoration":"var(--breadcrumb-link-decor)","--breadcrumb-link-decor":"none","&:not([aria-current=page])":{"cursor":"pointer","_hover":{"--breadcrumb-link-decor":"underline"},"_focusVisible":{"boxShadow":"outline"}}}}},"Button":{"baseStyle":{"lineHeight":"1.2","borderRadius":"md","fontWeight":"semibold","transitionProperty":"common","transitionDuration":"normal","_focusVisible":{"boxShadow":"outline"},"_disabled":{"opacity":0.4,"cursor":"not-allowed","boxShadow":"none"},"_hover":{"_disabled":{"bg":"initial"}},"rounded":"full"},"variants":{"unstyled":{"bg":"none","color":"inherit","display":"inline","lineHeight":"inherit","m":"0","p":"0"}},"sizes":{"lg":{"h":"12","minW":"12","fontSize":"lg","px":"6"},"md":{"h":"10","minW":"10","fontSize":"md","px":"4"},"sm":{"h":"8","minW":"8","fontSize":"sm","px":"3"},"xs":{"h":"6","minW":"6","fontSize":"xs","px":"2"}},"defaultProps":{"variant":"solid","size":"md","colorScheme":"emerald"}},"Checkbox":{"parts":["control","icon","container","label"],"sizes":{"sm":{"control":{"--checkbox-size":"sizes.3"},"label":{"fontSize":"sm"},"icon":{"fontSize":"3xs"}},"md":{"control":{"--checkbox-size":"sizes.4"},"label":{"fontSize":"md"},"icon":{"fontSize":"2xs"}},"lg":{"control":{"--checkbox-size":"sizes.5"},"label":{"fontSize":"lg"},"icon":{"fontSize":"2xs"}}},"defaultProps":{"size":"md","colorScheme":"blue"}},"CloseButton":{"baseStyle":{"w":["var(--close-button-size)"],"h":["var(--close-button-size)"],"borderRadius":"md","transitionProperty":"common","transitionDuration":"normal","_disabled":{"opacity":0.4,"cursor":"not-allowed","boxShadow":"none"},"_hover":{"--close-button-bg":"colors.blackAlpha.100","_dark":{"--close-button-bg":"colors.whiteAlpha.100"}},"_active":{"--close-button-bg":"colors.blackAlpha.200","_dark":{"--close-button-bg":"colors.whiteAlpha.200"}},"_focusVisible":{"boxShadow":"outline"},"bg":"var(--close-button-bg)"},"sizes":{"lg":{"--close-button-size":"sizes.10","fontSize":"md"},"md":{"--close-button-size":"sizes.8","fontSize":"xs"},"sm":{"--close-button-size":"sizes.6","fontSize":"2xs"}},"defaultProps":{"size":"md"}},"Code":{"baseStyle":{"fontFamily":"mono","fontSize":"sm","px":"0.2em","borderRadius":"sm","bg":"var(--badge-bg)","color":"var(--badge-color)","boxShadow":"var(--badge-shadow)"},"variants":{},"defaultProps":{"variant":"subtle","colorScheme":"gray"}},"Container":{"baseStyle":{"w":"100%","mx":"auto","maxW":"prose","px":"4"}},"Divider":{"baseStyle":{"opacity":0.6,"borderColor":"inherit"},"variants":{"solid":{"borderStyle":"solid"},"dashed":{"borderStyle":"dashed"}},"defaultProps":{"variant":"solid"}},"Drawer":{"parts":["overlay","dialogContainer","dialog","header","closeButton","body","footer"],"sizes":{"xs":{"dialog":{"maxW":"xs"}},"sm":{"dialog":{"maxW":"md"}},"md":{"dialog":{"maxW":"lg"}},"lg":{"dialog":{"maxW":"2xl"}},"xl":{"dialog":{"maxW":"4xl"}},"full":{"dialog":{"maxW":"100vw","h":"100vh"}}},"defaultProps":{"size":"xs"}},"Editable":{"parts":["preview","input","textarea"],"baseStyle":{"preview":{"borderRadius":"md","py":"1","transitionProperty":"common","transitionDuration":"normal"},"input":{"borderRadius":"md","py":"1","transitionProperty":"common","transitionDuration":"normal","width":"full","_focusVisible":{"boxShadow":"outline"},"_placeholder":{"opacity":0.6}},"textarea":{"borderRadius":"md","py":"1","transitionProperty":"common","transitionDuration":"normal","width":"full","_focusVisible":{"boxShadow":"outline"},"_placeholder":{"opacity":0.6}}}},"Form":{"parts":["container","requiredIndicator","helperText"],"baseStyle":{"container":{"width":"100%","position":"relative"},"requiredIndicator":{"marginStart":"1","--form-control-color":"colors.red.500","_dark":{"--form-control-color":"colors.red.300"},"color":"var(--form-control-color)"},"helperText":{"mt":"2","--form-control-color":"colors.gray.600","_dark":{"--form-control-color":"colors.whiteAlpha.600"},"color":"var(--form-control-color)","lineHeight":"normal","fontSize":"sm"}}},"FormError":{"parts":["text","icon"],"baseStyle":{"text":{"--form-error-color":"colors.red.500","_dark":{"--form-error-color":"colors.red.300"},"color":"var(--form-error-color)","mt":"2","fontSize":"sm","lineHeight":"normal"},"icon":{"marginEnd":"0.5em","--form-error-color":"colors.red.500","_dark":{"--form-error-color":"colors.red.300"},"color":"var(--form-error-color)"}}},"FormLabel":{"baseStyle":{"fontSize":"md","marginEnd":"3","mb":"2","fontWeight":"medium","transitionProperty":"common","transitionDuration":"normal","opacity":1,"_disabled":{"opacity":0.4}}},"Heading":{"baseStyle":{"fontFamily":"heading","fontWeight":"bold"},"sizes":{"4xl":{"fontSize":["6xl",null,"7xl"],"lineHeight":1},"3xl":{"fontSize":["5xl",null,"6xl"],"lineHeight":1},"2xl":{"fontSize":["4xl",null,"5xl"],"lineHeight":[1.2,null,1]},"xl":{"fontSize":["3xl",null,"4xl"],"lineHeight":[1.33,null,1.2]},"lg":{"fontSize":["2xl",null,"3xl"],"lineHeight":[1.33,null,1.2]},"md":{"fontSize":"xl","lineHeight":1.2},"sm":{"fontSize":"md","lineHeight":1.2},"xs":{"fontSize":"sm","lineHeight":1.2}},"defaultProps":{"size":"xl"}},"Input":{"parts":["addon","field","element"],"baseStyle":{"field":{"width":"100%","minWidth":0,"outline":0,"position":"relative","appearance":"none","transitionProperty":"common","transitionDuration":"normal","_disabled":{"opacity":0.4,"cursor":"not-allowed"}}},"sizes":{"lg":{"field":{"fontSize":"lg","px":"4","h":"12","borderRadius":"md"},"addon":{"fontSize":"lg","px":"4","h":"12","borderRadius":"md"}},"md":{"field":{"fontSize":"md","px":"4","h":"10","borderRadius":"md"},"addon":{"fontSize":"md","px":"4","h":"10","borderRadius":"md"}},"sm":{"field":{"fontSize":"sm","px":"3","h":"8","borderRadius":"sm"},"addon":{"fontSize":"sm","px":"3","h":"8","borderRadius":"sm"}},"xs":{"field":{"fontSize":"xs","px":"2","h":"6","borderRadius":"sm"},"addon":{"fontSize":"xs","px":"2","h":"6","borderRadius":"sm"}}},"variants":{"unstyled":{"field":{"bg":"transparent","px":"0","height":"auto"},"addon":{"bg":"transparent","px":"0","height":"auto"}}},"defaultProps":{"size":"md","variant":"outline"}},"Kbd":{"baseStyle":{"--kbd-bg":"colors.gray.100","_dark":{"--kbd-bg":"colors.whiteAlpha.100"},"bg":"var(--kbd-bg)","borderRadius":"md","borderWidth":"1px","borderBottomWidth":"3px","fontSize":"0.8em","fontWeight":"bold","lineHeight":"normal","px":"0.4em","whiteSpace":"nowrap"}},"Link":{"baseStyle":{"transitionProperty":"common","transitionDuration":"fast","transitionTimingFunction":"ease-out","cursor":"pointer","textDecoration":"none","outline":"none","color":"inherit","_hover":{"textDecoration":"underline"},"_focusVisible":{"boxShadow":"outline"}}},"List":{"parts":["container","item","icon"],"baseStyle":{"icon":{"marginEnd":"2","display":"inline","verticalAlign":"text-bottom"}}},"Menu":{"parts":["button","list","item","groupTitle","command","divider"],"baseStyle":{"button":{"transitionProperty":"common","transitionDuration":"normal"},"list":{"--menu-bg":"#fff","--menu-shadow":"shadows.sm","_dark":{"--menu-bg":"colors.gray.700","--menu-shadow":"shadows.dark-lg"},"color":"inherit","minW":"3xs","py":"2","zIndex":1,"borderRadius":"md","borderWidth":"1px","bg":"var(--menu-bg)","boxShadow":"var(--menu-shadow)"},"item":{"py":"1.5","px":"3","transitionProperty":"background","transitionDuration":"ultra-fast","transitionTimingFunction":"ease-in","_focus":{"--menu-bg":"colors.gray.100","_dark":{"--menu-bg":"colors.whiteAlpha.100"}},"_active":{"--menu-bg":"colors.gray.200","_dark":{"--menu-bg":"colors.whiteAlpha.200"}},"_expanded":{"--menu-bg":"colors.gray.100","_dark":{"--menu-bg":"colors.whiteAlpha.100"}},"_disabled":{"opacity":0.4,"cursor":"not-allowed"},"bg":"var(--menu-bg)"},"groupTitle":{"mx":4,"my":2,"fontWeight":"semibold","fontSize":"sm"},"command":{"opacity":0.6},"divider":{"border":0,"borderBottom":"1px solid","borderColor":"inherit","my":"2","opacity":0.6}}},"Modal":{"parts":["overlay","dialogContainer","dialog","header","closeButton","body","footer"],"sizes":{"xs":{"dialog":{"maxW":"xs"}},"sm":{"dialog":{"maxW":"sm"}},"md":{"dialog":{"maxW":"md"}},"lg":{"dialog":{"maxW":"lg"}},"xl":{"dialog":{"maxW":"xl"}},"2xl":{"dialog":{"maxW":"2xl"}},"3xl":{"dialog":{"maxW":"3xl"}},"4xl":{"dialog":{"maxW":"4xl"}},"5xl":{"dialog":{"maxW":"5xl"}},"6xl":{"dialog":{"maxW":"6xl"}},"full":{"dialog":{"maxW":"100vw","minH":"$100vh","my":"0","borderRadius":"0"}}},"defaultProps":{"size":"md"}},"NumberInput":{"parts":["root","field","stepperGroup","stepper"],"sizes":{"xs":{"field":{"fontSize":"xs","px":"2","h":"6","borderRadius":"sm","paddingInlineEnd":"var(--number-input-input-padding)","verticalAlign":"top"},"stepper":{"fontSize":"calc(0.75rem * 0.75)","_first":{"borderTopEndRadius":"sm"},"_last":{"borderBottomEndRadius":"sm","mt":"-1px","borderTopWidth":1}}},"sm":{"field":{"fontSize":"sm","px":"3","h":"8","borderRadius":"sm","paddingInlineEnd":"var(--number-input-input-padding)","verticalAlign":"top"},"stepper":{"fontSize":"calc(0.875rem * 0.75)","_first":{"borderTopEndRadius":"sm"},"_last":{"borderBottomEndRadius":"sm","mt":"-1px","borderTopWidth":1}}},"md":{"field":{"fontSize":"md","px":"4","h":"10","borderRadius":"md","paddingInlineEnd":"var(--number-input-input-padding)","verticalAlign":"top"},"stepper":{"fontSize":"calc(1rem * 0.75)","_first":{"borderTopEndRadius":"md"},"_last":{"borderBottomEndRadius":"md","mt":"-1px","borderTopWidth":1}}},"lg":{"field":{"fontSize":"lg","px":"4","h":"12","borderRadius":"md","paddingInlineEnd":"var(--number-input-input-padding)","verticalAlign":"top"},"stepper":{"fontSize":"calc(1.125rem * 0.75)","_first":{"borderTopEndRadius":"md"},"_last":{"borderBottomEndRadius":"md","mt":"-1px","borderTopWidth":1}}}},"variants":{"unstyled":{"field":{"bg":"transparent","px":"0","height":"auto"},"addon":{"bg":"transparent","px":"0","height":"auto"}}},"defaultProps":{"size":"md","variant":"outline"}},"PinInput":{"baseStyle":{"width":"100%","minWidth":0,"outline":0,"position":"relative","appearance":"none","transitionProperty":"common","transitionDuration":"normal","_disabled":{"opacity":0.4,"cursor":"not-allowed"},"textAlign":"center"},"sizes":{"lg":{"fontSize":"lg","w":12,"h":12,"borderRadius":"md"},"md":{"fontSize":"md","w":10,"h":10,"borderRadius":"md"},"sm":{"fontSize":"sm","w":8,"h":8,"borderRadius":"sm"},"xs":{"fontSize":"xs","w":6,"h":6,"borderRadius":"sm"}},"variants":{"unstyled":{"bg":"transparent","px":"0","height":"auto"}},"defaultProps":{"size":"md","variant":"outline"}},"Popover":{"parts":["content","header","body","footer","popper","arrow","closeButton"],"baseStyle":{"popper":{"zIndex":10},"content":{"--popper-bg":"colors.white","bg":"var(--popper-bg)","--popper-arrow-bg":"var(--popper-bg)","--popper-arrow-shadow-color":"colors.gray.200","_dark":{"--popper-bg":"colors.gray.700","--popper-arrow-shadow-color":"colors.whiteAlpha.300"},"width":"xs","border":"1px solid","borderColor":"inherit","borderRadius":"md","boxShadow":"sm","zIndex":"inherit","_focusVisible":{"outline":0,"boxShadow":"outline"}},"header":{"px":3,"py":2,"borderBottomWidth":"1px"},"body":{"px":3,"py":2},"footer":{"px":3,"py":2,"borderTopWidth":"1px"},"closeButton":{"position":"absolute","borderRadius":"md","top":1,"insetEnd":2,"padding":2}}},"Progress":{"parts":["label","filledTrack","track"],"sizes":{"xs":{"track":{"h":"1"}},"sm":{"track":{"h":"2"}},"md":{"track":{"h":"3"}},"lg":{"track":{"h":"4"}}},"defaultProps":{"size":"md","colorScheme":"blue"}},"Radio":{"parts":["container","control","label"],"sizes":{"md":{"control":{"w":"4","h":"4"},"label":{"fontSize":"md"}},"lg":{"control":{"w":"5","h":"5"},"label":{"fontSize":"lg"}},"sm":{"control":{"width":"3","height":"3"},"label":{"fontSize":"sm"}}},"defaultProps":{"size":"md","colorScheme":"blue"}},"Select":{"parts":["field","icon"],"baseStyle":{"field":{"width":"100%","minWidth":0,"outline":0,"position":"relative","appearance":"none","transitionProperty":"common","transitionDuration":"normal","_disabled":{"opacity":0.4,"cursor":"not-allowed"},"paddingBottom":"1px","lineHeight":"normal","bg":"var(--select-bg)","--select-bg":"colors.white","_dark":{"--select-bg":"colors.gray.700"},"> option, > optgroup":{"bg":"var(--select-bg)"}},"icon":{"width":"6","height":"100%","insetEnd":"2","position":"relative","color":"currentColor","fontSize":"xl","_disabled":{"opacity":0.5}}},"sizes":{"lg":{"field":{"fontSize":"lg","px":"4","h":"12","borderRadius":"md","paddingInlineEnd":"8"},"addon":{"fontSize":"lg","px":"4","h":"12","borderRadius":"md"}},"md":{"field":{"fontSize":"md","px":"4","h":"10","borderRadius":"md","paddingInlineEnd":"8"},"addon":{"fontSize":"md","px":"4","h":"10","borderRadius":"md"}},"sm":{"field":{"fontSize":"sm","px":"3","h":"8","borderRadius":"sm","paddingInlineEnd":"8"},"addon":{"fontSize":"sm","px":"3","h":"8","borderRadius":"sm"}},"xs":{"field":{"fontSize":"xs","px":"2","h":"6","borderRadius":"sm","paddingInlineEnd":"8"},"addon":{"fontSize":"xs","px":"2","h":"6","borderRadius":"sm"},"icon":{"insetEnd":"1"}}},"variants":{"unstyled":{"field":{"bg":"transparent","px":"0","height":"auto"},"addon":{"bg":"transparent","px":"0","height":"auto"}}},"defaultProps":{"size":"md","variant":"outline"}},"Skeleton":{"baseStyle":{"--skeleton-start-color":"colors.gray.100","--skeleton-end-color":"colors.gray.400","_dark":{"--skeleton-start-color":"colors.gray.800","--skeleton-end-color":"colors.gray.600"},"background":"var(--skeleton-start-color)","borderColor":"var(--skeleton-end-color)","opacity":0.7,"borderRadius":"sm"}},"SkipLink":{"baseStyle":{"borderRadius":"md","fontWeight":"semibold","_focusVisible":{"boxShadow":"outline","padding":"4","position":"fixed","top":"6","insetStart":"6","--skip-link-bg":"colors.white","_dark":{"--skip-link-bg":"colors.gray.700"},"bg":"var(--skip-link-bg)"}}},"Slider":{"parts":["container","track","thumb","filledTrack","mark"],"sizes":{"lg":{"container":{"--slider-thumb-size":"sizes.4","--slider-track-size":"sizes.1"}},"md":{"container":{"--slider-thumb-size":"sizes.3.5","--slider-track-size":"sizes.1"}},"sm":{"container":{"--slider-thumb-size":"sizes.2.5","--slider-track-size":"sizes.0.5"}}},"defaultProps":{"size":"md","colorScheme":"blue"}},"Spinner":{"baseStyle":{"width":["var(--spinner-size)"],"height":["var(--spinner-size)"]},"sizes":{"xs":{"--spinner-size":"sizes.3"},"sm":{"--spinner-size":"sizes.4"},"md":{"--spinner-size":"sizes.6"},"lg":{"--spinner-size":"sizes.8"},"xl":{"--spinner-size":"sizes.12"}},"defaultProps":{"size":"md"}},"Stat":{"parts":["container","label","helpText","number","icon"],"baseStyle":{"container":{},"label":{"fontWeight":"medium"},"helpText":{"opacity":0.8,"marginBottom":"2"},"number":{"verticalAlign":"baseline","fontWeight":"semibold"},"icon":{"marginEnd":1,"w":"3.5","h":"3.5","verticalAlign":"middle"}},"sizes":{"md":{"label":{"fontSize":"sm"},"helpText":{"fontSize":"sm"},"number":{"fontSize":"2xl"}}},"defaultProps":{"size":"md"}},"Switch":{"parts":["container","track","thumb"],"sizes":{"sm":{"container":{"--switch-track-width":"1.375rem","--switch-track-height":"sizes.3"}},"md":{"container":{"--switch-track-width":"1.875rem","--switch-track-height":"sizes.4"}},"lg":{"container":{"--switch-track-width":"2.875rem","--switch-track-height":"sizes.6"}}},"defaultProps":{"size":"md","colorScheme":"blue"}},"Table":{"parts":["table","thead","tbody","tr","th","td","tfoot","caption"],"baseStyle":{"table":{"fontVariantNumeric":"lining-nums tabular-nums","borderCollapse":"collapse","width":"full"},"th":{"fontFamily":"heading","fontWeight":"bold","textTransform":"uppercase","letterSpacing":"wider","textAlign":"start"},"td":{"textAlign":"start"},"caption":{"mt":4,"fontFamily":"heading","textAlign":"center","fontWeight":"medium"}},"variants":{"unstyled":{}},"sizes":{"sm":{"th":{"px":"4","py":"1","lineHeight":"4","fontSize":"xs"},"td":{"px":"4","py":"2","fontSize":"sm","lineHeight":"4"},"caption":{"px":"4","py":"2","fontSize":"xs"}},"md":{"th":{"px":"6","py":"3","lineHeight":"4","fontSize":"xs"},"td":{"px":"6","py":"4","lineHeight":"5"},"caption":{"px":"6","py":"2","fontSize":"sm"}},"lg":{"th":{"px":"8","py":"4","lineHeight":"5","fontSize":"sm"},"td":{"px":"8","py":"5","lineHeight":"6"},"caption":{"px":"6","py":"2","fontSize":"md"}}},"defaultProps":{"variant":"simple","size":"md","colorScheme":"gray"}},"Tabs":{"parts":["root","tab","tablist","tabpanel","tabpanels","indicator"],"sizes":{"sm":{"tab":{"py":1,"px":4,"fontSize":"sm"}},"md":{"tab":{"fontSize":"md","py":2,"px":4}},"lg":{"tab":{"fontSize":"lg","py":3,"px":4}}},"variants":{"unstyled":{}},"defaultProps":{"size":"md","variant":"line","colorScheme":"blue"}},"Tag":{"parts":["container","label","closeButton"],"variants":{},"baseStyle":{"container":{"fontWeight":"medium","lineHeight":1.2,"outline":0,"color":"var(--badge-color)","bg":"var(--badge-bg)","boxShadow":"var(--badge-shadow)","borderRadius":"md","_focusVisible":{"boxShadow":"outline"}},"label":{"lineHeight":1.2,"overflow":"visible"},"closeButton":{"fontSize":"lg","w":"5","h":"5","transitionProperty":"common","transitionDuration":"normal","borderRadius":"full","marginStart":"1.5","marginEnd":"-1","opacity":0.5,"_disabled":{"opacity":0.4},"_focusVisible":{"boxShadow":"outline","bg":"rgba(0, 0, 0, 0.14)"},"_hover":{"opacity":0.8},"_active":{"opacity":1}}},"sizes":{"sm":{"container":{"minH":"5","minW":"5","fontSize":"xs","px":"2"},"closeButton":{"marginEnd":"-2px","marginStart":"0.35rem"}},"md":{"container":{"minH":"6","minW":"6","fontSize":"sm","px":"2"}},"lg":{"container":{"minH":"8","minW":"8","fontSize":"md","px":"3"}}},"defaultProps":{"size":"md","variant":"subtle","colorScheme":"gray"}},"Textarea":{"baseStyle":{"width":"100%","minWidth":0,"outline":0,"position":"relative","appearance":"none","transitionProperty":"common","transitionDuration":"normal","_disabled":{"opacity":0.4,"cursor":"not-allowed"},"paddingY":"2","minHeight":"20","lineHeight":"short","verticalAlign":"top"},"sizes":{"xs":{"fontSize":"xs","px":"2","h":"6","borderRadius":"sm"},"sm":{"fontSize":"sm","px":"3","h":"8","borderRadius":"sm"},"md":{"fontSize":"md","px":"4","h":"10","borderRadius":"md"},"lg":{"fontSize":"lg","px":"4","h":"12","borderRadius":"md"}},"variants":{"unstyled":{"bg":"transparent","px":"0","height":"auto"}},"defaultProps":{"size":"md","variant":"outline"}},"Tooltip":{"baseStyle":{"bg":"var(--tooltip-bg)","color":"var(--tooltip-fg)","--tooltip-bg":"colors.gray.700","--tooltip-fg":"colors.whiteAlpha.900","_dark":{"--tooltip-bg":"colors.gray.300","--tooltip-fg":"colors.gray.900"},"--popper-arrow-bg":"var(--tooltip-bg)","px":"2","py":"0.5","borderRadius":"sm","fontWeight":"medium","fontSize":"sm","boxShadow":"md","maxW":"xs","zIndex":"tooltip"}},"Card":{"parts":["container","header","body","footer"],"baseStyle":{"container":{"--card-bg":"colors.chakra-body-bg","backgroundColor":"var(--card-bg)","boxShadow":"var(--card-shadow)","borderRadius":"var(--card-radius)","color":"chakra-body-text","borderWidth":"var(--card-border-width, 0)","borderColor":"var(--card-border-color)"},"body":{"padding":"var(--card-padding)","flex":"1 1 0%"},"header":{"padding":"var(--card-padding)"},"footer":{"padding":"var(--card-padding)"}},"variants":{"elevated":{"container":{"--card-shadow":"shadows.base","_dark":{"--card-bg":"colors.gray.700"}}},"outline":{"container":{"--card-border-width":"1px","--card-border-color":"colors.chakra-border-color"}},"filled":{"container":{"--card-bg":"colors.chakra-subtle-bg"}},"unstyled":{"body":{"--card-padding":0},"header":{"--card-padding":0},"footer":{"--card-padding":0}}},"sizes":{"sm":{"container":{"--card-radius":"radii.base","--card-padding":"space.3"}},"md":{"container":{"--card-radius":"radii.md","--card-padding":"space.5"}},"lg":{"container":{"--card-radius":"radii.xl","--card-padding":"space.7"}}},"defaultProps":{"variant":"elevated","size":"md"}},"Stepper":{"parts":["stepper","step","title","description","indicator","separator","icon","number"],"sizes":{"xs":{"stepper":{"--stepper-indicator-size":"sizes.4","--stepper-icon-size":"sizes.3","--stepper-title-font-size":"fontSizes.xs","--stepper-description-font-size":"fontSizes.xs"}},"sm":{"stepper":{"--stepper-indicator-size":"sizes.6","--stepper-icon-size":"sizes.4","--stepper-title-font-size":"fontSizes.sm","--stepper-description-font-size":"fontSizes.xs"}},"md":{"stepper":{"--stepper-indicator-size":"sizes.8","--stepper-icon-size":"sizes.5","--stepper-title-font-size":"fontSizes.md","--stepper-description-font-size":"fontSizes.sm"}},"lg":{"stepper":{"--stepper-indicator-size":"sizes.10","--stepper-icon-size":"sizes.6","--stepper-title-font-size":"fontSizes.lg","--stepper-description-font-size":"fontSizes.md"}}},"defaultProps":{"size":"md","colorScheme":"blue"}}},"styles":{"global":{"body":{"fontFamily":"body","color":"chakra-body-text","bg":"chakra-body-bg","transitionProperty":"background-color","transitionDuration":"normal","lineHeight":"base"},"*::placeholder":{"color":"chakra-placeholder-color"},"*, *::before, &::after":{"borderColor":"chakra-border-color"},"html, body":{"color":"bodyText","bg":"bodyBg","fontFamily":"body !important"},"table":{"width":"100%","marginY":"8","th":{"bg":"gray.100"},"th, td":{"borderWidth":"1px","py":"3","px":"5","textAlign":"start"}},"mark":{"bg":"transparent"},".chakra-prose":{"output":{"fontFeatureSettings":"tnum","fontVariantNumeric":"tabular-nums"},"li:not([role])":{"marginY":"1"},"ol:not([role]), ul:not([role])":{"marginY":"5","paddingLeft":"4"},"h2,h3,h4":{"scrollMarginTop":"24","&:hover":{"a.anchor":{"opacity":1}},"a:focus":{"opacity":1}},"p, li:not([role])":{"lineHeight":"tall"},"p + p":{"marginTop":"6"},"a.anchor":{"opacity":0,"color":"green.400","transition":"opacity 0.2s ease-in-out","marginX":"3","&:before":{"content":"\"#\""},"&:hover":{"opacity":"1"}}}}},"config":{"useSystemColorMode":false,"initialColorMode":"light","cssVarPrefix":"chakra"},"textStyles":{"heading":{"fontFamily":"heading","textAlign":"center","fontWeight":"bold","letterSpacing":"-0.015em","lineHeight":"1.24","fontSize":{"base":"2rem","md":"3.5rem"}},"heading-2":{"fontFamily":"heading","textAlign":"center","fontWeight":"bold","letterSpacing":"-0.015em","lineHeight":"1.24","fontSize":{"base":"1.75rem","md":"2.75rem"}},"caps":{"textTransform":"uppercase","fontSize":"sm","letterSpacing":"widest","fontWeight":"bold"},"sidebarLink":{"display":"inline-block","paddingY":"1","transition":"color 0.2s ease-in-out","_activeLink":{"&:after":{"content":"''","position":"absolute","width":"100%","height":"1px","transform":"scaleX(1)","top":"85%","left":"0px","right":"0px","backgroundColor":"currentColor"},"fontWeight":"bold"}},"link":{"color":"textLink","cursor":"pointer","fontWeight":"medium","textDecoration":"underline","textDecorationColor":"cyan.default","textDecorationThickness":"1px","textUnderlineOffset":"2px","_hover":{"textDecorationThickness":"2px"}},"display":{"2xl":{"fontSize":{"base":"4xl","sm":"5xl","md":"7xl"},"fontWeight":"bold","lineHeight":"shorter","letterSpacing":"tight"},"xl":{"fontSize":{"base":"4xl","md":"6xl"},"fontWeight":"bold","lineHeight":"shorter","letterSpacing":"tight"},"lg":{"fontSize":{"base":"3xl","md":"4xl"},"fontWeight":"bold","letterSpacing":"tight","lineHeight":"1.2"},"md":{"fontSize":{"base":"xl","md":"2xl"},"fontWeight":"bold","lineHeight":"1.4","letterSpacing":"tight"},"sm":{"fontSize":"xl","fontWeight":"semibold","lineHeight":"1.5"},"xs":{"fontWeight":"semibold","lineHeight":"1.5"}},"text":{"2xl":{"fontSize":{"base":"xl","md":"2xl"},"lineHeight":"tall"},"xl":{"fontSize":{"base":"lg","md":"xl"},"lineHeight":"tall"},"lg":{"fontSize":"lg","lineHeight":"tall"},"md":{"fontSize":"16px","lineHeight":"24px"},"sm":{"fontSize":"14px","lineHeight":"20px"},"xs":{"fontSize":"12px","lineHeight":"18px"}}},"layerStyles":{"hero":{"notice":{"bg":"pillNoticeBg","color":"pillNoticeText","rounded":"full","px":3,"py":1}}}},"isBaseTheme":true,"icons":{"library":{"feArrowRight":{"prefix":"fe","iconName":"arrow-right","icon":[24,24,"<line x1=\"5\" y1=\"12\" x2=\"19\" y2=\"12\"></line><polyline points=\"12 5 19 12 12 19\"></polyline>","<svg xmlns=\"http://www.w3.org/2000/svg\" width=\"24\" height=\"24\" viewBox=\"0 0 24 24\" fill=\"none\" stroke=\"currentColor\" stroke-width=\"2\" stroke-linecap=\"round\" stroke-linejoin=\"round\" class=\"feather feather-arrow-right\"><path d=\"M5 12 L19 12\"/><path d=\"M12 5 L19 12 L12 19\"/></svg>","M5 12 L19 12 M12 5 L19 12 L12 19","\"xmlns\"=\"http=//www.w3.org/2000/svg\" \"width\"=\"24\" \"height\"=\"24\" \"fill\"=\"none\" \"stroke\"=\"currentColor\" \"stroke-width\"=2 \"stroke-linecap\"=\"round\" \"stroke-linejoin\"=\"round\"",{"xmlns":"http://www.w3.org/2000/svg","width":24,"height":24,"fill":"none","stroke":"currentColor","stroke-width":2,"stroke-linecap":"round","stroke-linejoin":"round"}]},"feBook":{"prefix":"fe","iconName":"book","icon":[24,24,"<path d=\"M4 19.5A2.5 2.5 0 0 1 6.5 17H20\"></path><path d=\"M6.5 2H20v20H6.5A2.5 2.5 0 0 1 4 19.5v-15A2.5 2.5 0 0 1 6.5 2z\"></path>","<svg xmlns=\"http://www.w3.org/2000/svg\" width=\"24\" height=\"24\" viewBox=\"0 0 24 24\" fill=\"none\" stroke=\"currentColor\" stroke-width=\"2\" stroke-linecap=\"round\" stroke-linejoin=\"round\" class=\"feather feather-book\"><path d=\"M4 19.5A2.5 2.5 0 0 1 6.5 17H20\"/><path d=\"M6.5 2H20v20H6.5A2.5 2.5 0 0 1 4 19.5v-15A2.5 2.5 0 0 1 6.5 2z\"/></svg>","M4 19.5A2.5 2.5 0 0 1 6.5 17H20 M6.5 2H20v20H6.5A2.5 2.5 0 0 1 4 19.5v-15A2.5 2.5 0 0 1 6.5 2z","\"xmlns\"=\"http=//www.w3.org/2000/svg\" \"width\"=\"24\" \"height\"=\"24\" \"fill\"=\"none\" \"stroke\"=\"currentColor\" \"stroke-width\"=2 \"stroke-linecap\"=\"round\" \"stroke-linejoin\"=\"round\"",{"xmlns":"http://www.w3.org/2000/svg","width":24,"height":24,"fill":"none","stroke":"currentColor","stroke-width":2,"stroke-linecap":"round","stroke-linejoin":"round"}]},"feCompass":{"prefix":"fe","iconName":"compass","icon":[24,24,"<circle cx=\"12\" cy=\"12\" r=\"10\"></circle><polygon points=\"16.24 7.76 14.12 14.12 7.76 16.24 9.88 9.88 16.24 7.76\"></polygon>","<svg xmlns=\"http://www.w3.org/2000/svg\" width=\"24\" height=\"24\" viewBox=\"0 0 24 24\" fill=\"none\" stroke=\"currentColor\" stroke-width=\"2\" stroke-linecap=\"round\" stroke-linejoin=\"round\" class=\"feather feather-compass\"><path d=\"M22 12 A10 10 0 0 1 12 22 A10 10 0 0 1 2 12 A10 10 0 0 1 22 12 z\"/><path d=\"M16.24 7.76 L14.12 14.12 L7.76 16.24 L9.88 9.88 L16.24 7.76 Z\"/></svg>","M22 12 A10 10 0 0 1 12 22 A10 10 0 0 1 2 12 A10 10 0 0 1 22 12 z M16.24 7.76 L14.12 14.12 L7.76 16.24 L9.88 9.88 L16.24 7.76 Z","\"xmlns\"=\"http=//www.w3.org/2000/svg\" \"width\"=\"24\" \"height\"=\"24\" \"fill\"=\"none\" \"stroke\"=\"currentColor\" \"stroke-width\"=2 \"stroke-linecap\"=\"round\" \"stroke-linejoin\"=\"round\"",{"xmlns":"http://www.w3.org/2000/svg","width":24,"height":24,"fill":"none","stroke":"currentColor","stroke-width":2,"stroke-linecap":"round","stroke-linejoin":"round"}]},"feExternalLink":{"prefix":"fe","iconName":"external-link","icon":[24,24,"<path d=\"M18 13v6a2 2 0 0 1-2 2H5a2 2 0 0 1-2-2V8a2 2 0 0 1 2-2h6\"></path><polyline points=\"15 3 21 3 21 9\"></polyline><line x1=\"10\" y1=\"14\" x2=\"21\" y2=\"3\"></line>","<svg xmlns=\"http://www.w3.org/2000/svg\" width=\"24\" height=\"24\" viewBox=\"0 0 24 24\" fill=\"none\" stroke=\"currentColor\" stroke-width=\"2\" stroke-linecap=\"round\" stroke-linejoin=\"round\" class=\"feather feather-external-link\"><path d=\"M18 13v6a2 2 0 0 1-2 2H5a2 2 0 0 1-2-2V8a2 2 0 0 1 2-2h6\"/><path d=\"M15 3 L21 3 L21 9\"/><path d=\"M10 14 L21 3\"/></svg>","M18 13v6a2 2 0 0 1-2 2H5a2 2 0 0 1-2-2V8a2 2 0 0 1 2-2h6 M15 3 L21 3 L21 9 M10 14 L21 3","\"xmlns\"=\"http=//www.w3.org/2000/svg\" \"width\"=\"24\" \"height\"=\"24\" \"fill\"=\"none\" \"stroke\"=\"currentColor\" \"stroke-width\"=2 \"stroke-linecap\"=\"round\" \"stroke-linejoin\"=\"round\"",{"xmlns":"http://www.w3.org/2000/svg","width":24,"height":24,"fill":"none","stroke":"currentColor","stroke-width":2,"stroke-linecap":"round","stroke-linejoin":"round"}]},"feGithub":{"prefix":"fe","iconName":"github","icon":[24,24,"<path d=\"M9 19c-5 1.5-5-2.5-7-3m14 6v-3.87a3.37 3.37 0 0 0-.94-2.61c3.14-.35 6.44-1.54 6.44-7A5.44 5.44 0 0 0 20 4.77 5.07 5.07 0 0 0 19.91 1S18.73.65 16 2.48a13.38 13.38 0 0 0-7 0C6.27.65 5.09 1 5.09 1A5.07 5.07 0 0 0 5 4.77a5.44 5.44 0 0 0-1.5 3.78c0 5.42 3.3 6.61 6.44 7A3.37 3.37 0 0 0 9 18.13V22\"></path>","<svg xmlns=\"http://www.w3.org/2000/svg\" width=\"24\" height=\"24\" viewBox=\"0 0 24 24\" fill=\"none\" stroke=\"currentColor\" stroke-width=\"2\" stroke-linecap=\"round\" stroke-linejoin=\"round\" class=\"feather feather-github\"><path d=\"M9 19c-5 1.5-5-2.5-7-3m14 6v-3.87a3.37 3.37 0 0 0-.94-2.61c3.14-.35 6.44-1.54 6.44-7A5.44 5.44 0 0 0 20 4.77 5.07 5.07 0 0 0 19.91 1S18.73.65 16 2.48a13.38 13.38 0 0 0-7 0C6.27.65 5.09 1 5.09 1A5.07 5.07 0 0 0 5 4.77a5.44 5.44 0 0 0-1.5 3.78c0 5.42 3.3 6.61 6.44 7A3.37 3.37 0 0 0 9 18.13V22\"/></svg>","M9 19c-5 1.5-5-2.5-7-3m14 6v-3.87a3.37 3.37 0 0 0-.94-2.61c3.14-.35 6.44-1.54 6.44-7A5.44 5.44 0 0 0 20 4.77 5.07 5.07 0 0 0 19.91 1S18.73.65 16 2.48a13.38 13.38 0 0 0-7 0C6.27.65 5.09 1 5.09 1A5.07 5.07 0 0 0 5 4.77a5.44 5.44 0 0 0-1.5 3.78c0 5.42 3.3 6.61 6.44 7A3.37 3.37 0 0 0 9 18.13V22","\"xmlns\"=\"http=//www.w3.org/2000/svg\" \"width\"=\"24\" \"height\"=\"24\" \"fill\"=\"none\" \"stroke\"=\"currentColor\" \"stroke-width\"=2 \"stroke-linecap\"=\"round\" \"stroke-linejoin\"=\"round\"",{"xmlns":"http://www.w3.org/2000/svg","width":24,"height":24,"fill":"none","stroke":"currentColor","stroke-width":2,"stroke-linecap":"round","stroke-linejoin":"round"}]},"feMenu":{"prefix":"fe","iconName":"menu","icon":[24,24,"<line x1=\"3\" y1=\"12\" x2=\"21\" y2=\"12\"></line><line x1=\"3\" y1=\"6\" x2=\"21\" y2=\"6\"></line><line x1=\"3\" y1=\"18\" x2=\"21\" y2=\"18\"></line>","<svg xmlns=\"http://www.w3.org/2000/svg\" width=\"24\" height=\"24\" viewBox=\"0 0 24 24\" fill=\"none\" stroke=\"currentColor\" stroke-width=\"2\" stroke-linecap=\"round\" stroke-linejoin=\"round\" class=\"feather feather-menu\"><path d=\"M3 12 L21 12\"/><path d=\"M3 6 L21 6\"/><path d=\"M3 18 L21 18\"/></svg>","M3 12 L21 12 M3 6 L21 6 M3 18 L21 18","\"xmlns\"=\"http=//www.w3.org/2000/svg\" \"width\"=\"24\" \"height\"=\"24\" \"fill\"=\"none\" \"stroke\"=\"currentColor\" \"stroke-width\"=2 \"stroke-linecap\"=\"round\" \"stroke-linejoin\"=\"round\"",{"xmlns":"http://www.w3.org/2000/svg","width":24,"height":24,"fill":"none","stroke":"currentColor","stroke-width":2,"stroke-linecap":"round","stroke-linejoin":"round"}]},"feMessageCircle":{"prefix":"fe","iconName":"message-circle","icon":[24,24,"<path d=\"M21 11.5a8.38 8.38 0 0 1-.9 3.8 8.5 8.5 0 0 1-7.6 4.7 8.38 8.38 0 0 1-3.8-.9L3 21l1.9-5.7a8.38 8.38 0 0 1-.9-3.8 8.5 8.5 0 0 1 4.7-7.6 8.38 8.38 0 0 1 3.8-.9h.5a8.48 8.48 0 0 1 8 8v.5z\"></path>","<svg xmlns=\"http://www.w3.org/2000/svg\" width=\"24\" height=\"24\" viewBox=\"0 0 24 24\" fill=\"none\" stroke=\"currentColor\" stroke-width=\"2\" stroke-linecap=\"round\" stroke-linejoin=\"round\" class=\"feather feather-message-circle\"><path d=\"M21 11.5a8.38 8.38 0 0 1-.9 3.8 8.5 8.5 0 0 1-7.6 4.7 8.38 8.38 0 0 1-3.8-.9L3 21l1.9-5.7a8.38 8.38 0 0 1-.9-3.8 8.5 8.5 0 0 1 4.7-7.6 8.38 8.38 0 0 1 3.8-.9h.5a8.48 8.48 0 0 1 8 8v.5z\"/></svg>","M21 11.5a8.38 8.38 0 0 1-.9 3.8 8.5 8.5 0 0 1-7.6 4.7 8.38 8.38 0 0 1-3.8-.9L3 21l1.9-5.7a8.38 8.38 0 0 1-.9-3.8 8.5 8.5 0 0 1 4.7-7.6 8.38 8.38 0 0 1 3.8-.9h.5a8.48 8.48 0 0 1 8 8v.5z","\"xmlns\"=\"http=//www.w3.org/2000/svg\" \"width\"=\"24\" \"height\"=\"24\" \"fill\"=\"none\" \"stroke\"=\"currentColor\" \"stroke-width\"=2 \"stroke-linecap\"=\"round\" \"stroke-linejoin\"=\"round\"",{"xmlns":"http://www.w3.org/2000/svg","width":24,"height":24,"fill":"none","stroke":"currentColor","stroke-width":2,"stroke-linecap":"round","stroke-linejoin":"round"}]},"feMoon":{"prefix":"fe","iconName":"moon","icon":[24,24,"<path d=\"M21 12.79A9 9 0 1 1 11.21 3 7 7 0 0 0 21 12.79z\"></path>","<svg xmlns=\"http://www.w3.org/2000/svg\" width=\"24\" height=\"24\" viewBox=\"0 0 24 24\" fill=\"none\" stroke=\"currentColor\" stroke-width=\"2\" stroke-linecap=\"round\" stroke-linejoin=\"round\" class=\"feather feather-moon\"><path d=\"M21 12.79A9 9 0 1 1 11.21 3 7 7 0 0 0 21 12.79z\"/></svg>","M21 12.79A9 9 0 1 1 11.21 3 7 7 0 0 0 21 12.79z","\"xmlns\"=\"http=//www.w3.org/2000/svg\" \"width\"=\"24\" \"height\"=\"24\" \"fill\"=\"none\" \"stroke\"=\"currentColor\" \"stroke-width\"=2 \"stroke-linecap\"=\"round\" \"stroke-linejoin\"=\"round\"",{"xmlns":"http://www.w3.org/2000/svg","width":24,"height":24,"fill":"none","stroke":"currentColor","stroke-width":2,"stroke-linecap":"round","stroke-linejoin":"round"}]},"fePackage":{"prefix":"fe","iconName":"package","icon":[24,24,"<line x1=\"16.5\" y1=\"9.4\" x2=\"7.5\" y2=\"4.21\"></line><path d=\"M21 16V8a2 2 0 0 0-1-1.73l-7-4a2 2 0 0 0-2 0l-7 4A2 2 0 0 0 3 8v8a2 2 0 0 0 1 1.73l7 4a2 2 0 0 0 2 0l7-4A2 2 0 0 0 21 16z\"></path><polyline points=\"3.27 6.96 12 12.01 20.73 6.96\"></polyline><line x1=\"12\" y1=\"22.08\" x2=\"12\" y2=\"12\"></line>","<svg xmlns=\"http://www.w3.org/2000/svg\" width=\"24\" height=\"24\" viewBox=\"0 0 24 24\" fill=\"none\" stroke=\"currentColor\" stroke-width=\"2\" stroke-linecap=\"round\" stroke-linejoin=\"round\" class=\"feather feather-package\"><path d=\"M16.5 9.4 L7.5 4.21\"/><path d=\"M21 16V8a2 2 0 0 0-1-1.73l-7-4a2 2 0 0 0-2 0l-7 4A2 2 0 0 0 3 8v8a2 2 0 0 0 1 1.73l7 4a2 2 0 0 0 2 0l7-4A2 2 0 0 0 21 16z\"/><path d=\"M3.27 6.96 L12 12.01 L20.73 6.96\"/><path d=\"M12 22.08 L12 12\"/></svg>","M16.5 9.4 L7.5 4.21 M21 16V8a2 2 0 0 0-1-1.73l-7-4a2 2 0 0 0-2 0l-7 4A2 2 0 0 0 3 8v8a2 2 0 0 0 1 1.73l7 4a2 2 0 0 0 2 0l7-4A2 2 0 0 0 21 16z M3.27 6.96 L12 12.01 L20.73 6.96 M12 22.08 L12 12","\"xmlns\"=\"http=//www.w3.org/2000/svg\" \"width\"=\"24\" \"height\"=\"24\" \"fill\"=\"none\" \"stroke\"=\"currentColor\" \"stroke-width\"=2 \"stroke-linecap\"=\"round\" \"stroke-linejoin\"=\"round\"",{"xmlns":"http://www.w3.org/2000/svg","width":24,"height":24,"fill":"none","stroke":"currentColor","stroke-width":2,"stroke-linecap":"round","stroke-linejoin":"round"}]},"feSearch":{"prefix":"fe","iconName":"search","icon":[24,24,"<circle cx=\"11\" cy=\"11\" r=\"8\"></circle><line x1=\"21\" y1=\"21\" x2=\"16.65\" y2=\"16.65\"></line>","<svg xmlns=\"http://www.w3.org/2000/svg\" width=\"24\" height=\"24\" viewBox=\"0 0 24 24\" fill=\"none\" stroke=\"currentColor\" stroke-width=\"2\" stroke-linecap=\"round\" stroke-linejoin=\"round\" class=\"feather feather-search\"><path d=\"M19 11 A8 8 0 0 1 11 19 A8 8 0 0 1 3 11 A8 8 0 0 1 19 11 z\"/><path d=\"M21 21 L16.65 16.65\"/></svg>","M19 11 A8 8 0 0 1 11 19 A8 8 0 0 1 3 11 A8 8 0 0 1 19 11 z M21 21 L16.65 16.65","\"xmlns\"=\"http=//www.w3.org/2000/svg\" \"width\"=\"24\" \"height\"=\"24\" \"fill\"=\"none\" \"stroke\"=\"currentColor\" \"stroke-width\"=2 \"stroke-linecap\"=\"round\" \"stroke-linejoin\"=\"round\"",{"xmlns":"http://www.w3.org/2000/svg","width":24,"height":24,"fill":"none","stroke":"currentColor","stroke-width":2,"stroke-linecap":"round","stroke-linejoin":"round"}]},"feStar":{"prefix":"fe","iconName":"star","icon":[24,24,"<polygon points=\"12 2 15.09 8.26 22 9.27 17 14.14 18.18 21.02 12 17.77 5.82 21.02 7 14.14 2 9.27 8.91 8.26 12 2\"></polygon>","<svg xmlns=\"http://www.w3.org/2000/svg\" width=\"24\" height=\"24\" viewBox=\"0 0 24 24\" fill=\"none\" stroke=\"currentColor\" stroke-width=\"2\" stroke-linecap=\"round\" stroke-linejoin=\"round\" class=\"feather feather-star\"><path d=\"M12 2 L15.09 8.26 L22 9.27 L17 14.14 L18.18 21.02 L12 17.77 L5.82 21.02 L7 14.14 L2 9.27 L8.91 8.26 L12 2 Z\"/></svg>","M12 2 L15.09 8.26 L22 9.27 L17 14.14 L18.18 21.02 L12 17.77 L5.82 21.02 L7 14.14 L2 9.27 L8.91 8.26 L12 2 Z","\"xmlns\"=\"http=//www.w3.org/2000/svg\" \"width\"=\"24\" \"height\"=\"24\" \"fill\"=\"none\" \"stroke\"=\"currentColor\" \"stroke-width\"=2 \"stroke-linecap\"=\"round\" \"stroke-linejoin\"=\"round\"",{"xmlns":"http://www.w3.org/2000/svg","width":24,"height":24,"fill":"none","stroke":"currentColor","stroke-width":2,"stroke-linecap":"round","stroke-linejoin":"round"}]},"feSun":{"prefix":"fe","iconName":"sun","icon":[24,24,"<circle cx=\"12\" cy=\"12\" r=\"5\"></circle><line x1=\"12\" y1=\"1\" x2=\"12\" y2=\"3\"></line><line x1=\"12\" y1=\"21\" x2=\"12\" y2=\"23\"></line><line x1=\"4.22\" y1=\"4.22\" x2=\"5.64\" y2=\"5.64\"></line><line x1=\"18.36\" y1=\"18.36\" x2=\"19.78\" y2=\"19.78\"></line><line x1=\"1\" y1=\"12\" x2=\"3\" y2=\"12\"></line><line x1=\"21\" y1=\"12\" x2=\"23\" y2=\"12\"></line><line x1=\"4.22\" y1=\"19.78\" x2=\"5.64\" y2=\"18.36\"></line><line x1=\"18.36\" y1=\"5.64\" x2=\"19.78\" y2=\"4.22\"></line>","<svg xmlns=\"http://www.w3.org/2000/svg\" width=\"24\" height=\"24\" viewBox=\"0 0 24 24\" fill=\"none\" stroke=\"currentColor\" stroke-width=\"2\" stroke-linecap=\"round\" stroke-linejoin=\"round\" class=\"feather feather-sun\"><path d=\"M17 12 A5 5 0 0 1 12 17 A5 5 0 0 1 7 12 A5 5 0 0 1 17 12 z\"/><path d=\"M12 1 L12 3\"/><path d=\"M12 21 L12 23\"/><path d=\"M4.22 4.22 L5.64 5.64\"/><path d=\"M18.36 18.36 L19.78 19.78\"/><path d=\"M1 12 L3 12\"/><path d=\"M21 12 L23 12\"/><path d=\"M4.22 19.78 L5.64 18.36\"/><path d=\"M18.36 5.64 L19.78 4.22\"/></svg>","M17 12 A5 5 0 0 1 12 17 A5 5 0 0 1 7 12 A5 5 0 0 1 17 12 z M12 1 L12 3 M12 21 L12 23 M4.22 4.22 L5.64 5.64 M18.36 18.36 L19.78 19.78 M1 12 L3 12 M21 12 L23 12 M4.22 19.78 L5.64 18.36 M18.36 5.64 L19.78 4.22","\"xmlns\"=\"http=//www.w3.org/2000/svg\" \"width\"=\"24\" \"height\"=\"24\" \"fill\"=\"none\" \"stroke\"=\"currentColor\" \"stroke-width\"=2 \"stroke-linecap\"=\"round\" \"stroke-linejoin\"=\"round\"",{"xmlns":"http://www.w3.org/2000/svg","width":24,"height":24,"fill":"none","stroke":"currentColor","stroke-width":2,"stroke-linecap":"round","stroke-linejoin":"round"}]}},"extend":{"discord":{"path":"<path fill=\"currentColor\" d=\"M107.75 125.001s-4.5-5.375-8.25-10.125c16.375-4.625 22.625-14.875 22.625-14.875-5.125 3.375-10 5.75-14.375 7.375-6.25 2.625-12.25 4.375-18.125 5.375-12 2.25-23 1.625-32.375-.125-7.125-1.375-13.25-3.375-18.375-5.375-2.875-1.125-6-2.5-9.125-4.25-.375-.25-.75-.375-1.125-.625-.25-.125-.375-.25-.5-.375-2.25-1.25-3.5-2.125-3.5-2.125s6 10 21.875 14.75c-3.75 4.75-8.375 10.375-8.375 10.375-27.625-.875-38.125-19-38.125-19 0-40.25 18-72.875 18-72.875 18-13.5 35.125-13.125 35.125-13.125l1.25 1.5c-22.5 6.5-32.875 16.375-32.875 16.375s2.75-1.5 7.375-3.625c13.375-5.875 24-7.5 28.375-7.875.75-.125 1.375-.25 2.125-.25 7.625-1 16.25-1.25 25.25-.25 11.875 1.375 24.625 4.875 37.625 12 0 0-9.875-9.375-31.125-15.875l1.75-2S110 19.626 128 33.126c0 0 18 32.625 18 72.875 0 0-10.625 18.125-38.25 19zM49.625 66.626c-7.125 0-12.75 6.25-12.75 13.875s5.75 13.875 12.75 13.875c7.125 0 12.75-6.25 12.75-13.875.125-7.625-5.625-13.875-12.75-13.875zm45.625 0c-7.125 0-12.75 6.25-12.75 13.875s5.75 13.875 12.75 13.875c7.125 0 12.75-6.25 12.75-13.875s-5.625-13.875-12.75-13.875z\" fillRule=\"nonzero\" />","viewBox":"0 0 146 146"},"youtube":{"path":"<path d=\"M23.498 6.186a3.016 3.016 0 0 0-2.122-2.136C19.505 3.545 12 3.545 12 3.545s-7.505 0-9.377.505A3.017 3.017 0 0 0 .502 6.186C0 8.07 0 12 0 12s0 3.93.502 5.814a3.016 3.016 0 0 0 2.122 2.136c1.871.505 9.376.505 9.376.505s7.505 0 9.377-.505a3.015 3.015 0 0 0 2.122-2.136C24 15.93 24 12 24 12s0-3.93-.502-5.814zM9.545 15.568V8.432L15.818 12l-6.273 3.568z\" fill=\"currentColor\"></path>","viewbox":"0 0 24 24"},"twitter":{"path":"<path d=\"M22.46 6c-.77.35-1.6.58-2.46.69c.88-.53 1.56-1.37 1.88-2.38c-.83.5-1.75.85-2.72 1.05C18.37 4.5 17.26 4 16 4c-2.35 0-4.27 1.92-4.27 4.29c0 .34.04.67.11.98C8.28 9.09 5.11 7.38 3 4.79c-.37.63-.58 1.37-.58 2.15c0 1.49.75 2.81 1.91 3.56c-.71 0-1.37-.2-1.95-.5v.03c0 2.08 1.48 3.82 3.44 4.21a4.22 4.22 0 0 1-1.93.07a4.28 4.28 0 0 0 4 2.98a8.521 8.521 0 0 1-5.33 1.84c-.34 0-.68-.02-1.02-.06C3.44 20.29 5.7 21 8.12 21C16 21 20.33 14.46 20.33 8.79c0-.19 0-.37-.01-.56c.84-.6 1.56-1.36 2.14-2.23z\" fill=\"currentColor\"></path>","viewBox":"0 0 24 24"},"heart":{"path":"<path d=\"M896 1536q-26 0-44-18L228 916q-10-8-27.5-26T145 824.5T77 727T23.5 606T0 468q0-220 127-344T478 0q62 0 126.5 21.5t120 58T820 148t76 68q36-36 76-68t95.5-68.5t120-58T1314 0q224 0 351 124t127 344q0 221-229 450l-623 600q-18 18-44 18z\" fill=\"currentColor\"></path>","viewBox":"0 0 1792 1536"},"npm":{"path":"<path d=\"M157.538 164.103h65.641v-32.82h65.642V0H157.538v164.103zM223.18 32.82H256v65.64h-32.82v-65.64zM315.077 0v131.282h65.64V32.821h32.821v98.461h32.821V32.821h32.82v98.461H512V0H315.077zM0 131.282h65.641V32.821h32.82v98.461h32.821V0H0v131.282z\" fill=\"currentColor\">","viewBox":"0 0 512 165"},"storybook":{"path":"<path d=\"M9.872 293.324L.012 30.574C-.315 21.895 6.338 14.54 15.005 14L238.494.032c8.822-.552 16.42 6.153 16.972 14.975c.02.332.031.665.031.998v286.314c0 8.839-7.165 16.004-16.004 16.004c-.24 0-.48-.005-.718-.016l-213.627-9.595c-8.32-.373-14.963-7.065-15.276-15.388z\" id=\"IconifyId-179377ab348-8608e7-6\"></path></defs><mask id=\"IconifyId-179377ab348-8608e7-7\" fill=\"#fff\"><use xlink:href=\"#IconifyId-179377ab348-8608e7-6\"></use></mask><use fill=\"#FF4785\" xlink:href=\"#IconifyId-179377ab348-8608e7-6\"></use><path d=\"M188.665 39.127l1.527-36.716L220.884 0l1.322 37.863a2.387 2.387 0 0 1-3.864 1.96l-11.835-9.325l-14.013 10.63a2.387 2.387 0 0 1-3.829-2.001zm-39.251 80.853c0 6.227 41.942 3.243 47.572-1.131c0-42.402-22.752-64.684-64.415-64.684c-41.662 0-65.005 22.628-65.005 56.57c0 59.117 79.78 60.249 79.78 92.494c0 9.052-4.433 14.426-14.184 14.426c-12.705 0-17.729-6.49-17.138-28.552c0-4.786-48.458-6.278-49.936 0c-3.762 53.466 29.548 68.887 67.665 68.887c36.935 0 65.892-19.687 65.892-55.326c0-63.36-80.961-61.663-80.961-93.06c0-12.728 9.455-14.425 15.07-14.425c5.909 0 16.546 1.042 15.66 24.801z\" fill=\"#FFF\" mask=\"url(#IconifyId-179377ab348-8608e7-7)\"></path>","viewBox":"0 0 256 319"},"edit":{"path":"<path d=\"M3 17.25V21h3.75L17.81 9.94l-3.75-3.75L3 17.25zM20.71 7.04a.996.996 0 0 0 0-1.41l-2.34-2.34a.996.996 0 0 0-1.41 0l-1.83 1.83l3.75 3.75l1.83-1.83z\" fill=\"currentColor\"></path>","viewBox":"0 0 24 24"},"menu":{"path":"<path fill=\"currentColor\" d=\"M904 160H120c-4.4 0-8 3.6-8 8v64c0 4.4 3.6 8 8 8h784c4.4 0 8-3.6 8-8v-64c0-4.4-3.6-8-8-8zm0 624H120c-4.4 0-8 3.6-8 8v64c0 4.4 3.6 8 8 8h784c4.4 0 8-3.6 8-8v-64c0-4.4-3.6-8-8-8zm0-312H120c-4.4 0-8 3.6-8 8v64c0 4.4 3.6 8 8 8h784c4.4 0 8-3.6 8-8v-64c0-4.4-3.6-8-8-8z\"></path>","viewBox":"0 0 1024 1024"},"chevronLeft":{"path":"<path fill=\"currentColor\" d=\"M15.41 7.41L14 6l-6 6 6 6 1.41-1.41L10.83 12z\"></path>","viewBox":"0 0 24 24"},"chevronRight":{"path":"<path fill=\"currentColor\" d=\"M10 6L8.59 7.41 13.17 12l-4.58 4.59L10 18l6-6z\"></path>","viewBox":"0 0 24 24"},"accessibilityAlt":{"path":"<path fill=\"currentColor\" d=\"M23 14v-2H9v2h5v2.734l-3.868 6.77l1.736.992L15.58 18h.84l3.712 6.496l1.736-.992L18 16.734V14h5z\"/><circle cx=\"16\" cy=\"9\" r=\"2\" fill=\"currentColor\"/><path fill=\"currentColor\" d=\"M16 30a14 14 0 1 1 14-14a14.016 14.016 0 0 1-14 14Zm0-26a12 12 0 1 0 12 12A12.014 12.014 0 0 0 16 4Z\"/>","viewBox":"0 0 32 32"},"cube":{"path":"<path fill=\"currentColor\" d=\"m28.504 8.136l-12-7a1 1 0 0 0-1.008 0l-12 7A1 1 0 0 0 3 9v14a1 1 0 0 0 .496.864l12 7a1 1 0 0 0 1.008 0l12-7A1 1 0 0 0 29 23V9a1 1 0 0 0-.496-.864ZM16 3.158L26.016 9L16 14.842L5.984 9ZM5 10.74l10 5.833V28.26L5 22.426Zm12 17.52V16.574l10-5.833v11.685Z\"/>","viewBox":"0 0 32 32"},"colorPalette":{"path":"<circle cx=\"10\" cy=\"12\" r=\"2\" fill=\"currentColor\"/><circle cx=\"16\" cy=\"9\" r=\"2\" fill=\"currentColor\"/><circle cx=\"22\" cy=\"12\" r=\"2\" fill=\"currentColor\"/><circle cx=\"23\" cy=\"18\" r=\"2\" fill=\"currentColor\"/><circle cx=\"19\" cy=\"23\" r=\"2\" fill=\"currentColor\"/><path fill=\"currentColor\" d=\"M16.54 2A14 14 0 0 0 2 16a4.82 4.82 0 0 0 6.09 4.65l1.12-.31a3 3 0 0 1 3.79 2.9V27a3 3 0 0 0 3 3a14 14 0 0 0 14-14.54A14.05 14.05 0 0 0 16.54 2Zm8.11 22.31A11.93 11.93 0 0 1 16 28a1 1 0 0 1-1-1v-3.76a5 5 0 0 0-5-5a5.07 5.07 0 0 0-1.33.18l-1.12.31A2.82 2.82 0 0 1 4 16A12 12 0 0 1 16.47 4A12.18 12.18 0 0 1 28 15.53a11.89 11.89 0 0 1-3.35 8.79Z\"/>","viewBox":"0 0 32 32"}}},"cssReset":true}},"content":{"sources":{},"ignores":[],"locales":[],"highlight":false,"navigation":{"fields":[]},"documentDriven":false,"experimental":{"clientDB":false,"stripQueryParameters":false,"advancedIgnoresPattern":false}},"components":[{"name":"CarbonAd","path":"components/content/CarbonAd.vue","meta":{"props":[],"slots":[],"events":[]}},{"name":"CodeEditor","path":"components/content/CodeEditor.vue","meta":{"props":[],"slots":[],"events":[]}},{"name":"DiscordBanner","path":"components/content/DiscordBanner.vue","meta":{"props":[],"slots":[],"events":[]}},{"name":"CodeEditorLayout","path":"components/content/Editor/CodeEditorLayout.vue","meta":{"props":[],"slots":[],"events":[]}},{"name":"CodeEditorParts","path":"components/content/Editor/CodeEditorParts.tsx","meta":{"props":[],"slots":[],"events":[]}},{"name":"CodeHighlight","path":"components/content/Editor/CodeHighlight.vue","meta":{"props":[],"slots":[],"events":[]}},{"name":"CodeContainer","path":"components/content/Editor/code-container.tsx","meta":{"props":[],"slots":[],"events":[]}},{"name":"CopyButton","path":"components/content/Editor/copy-button.tsx","meta":{"props":[],"slots":[],"events":[]}},{"name":"EditableNotice","path":"components/content/Editor/editable-notice.tsx","meta":{"props":[],"slots":[],"events":[]}},{"name":"FrameworkCard","path":"components/content/FrameworkList/FrameworkCard.vue","meta":{"props":[],"slots":[],"events":[]}},{"name":"FrameworkList","path":"components/content/FrameworkList/FrameworkList.vue","meta":{"props":[],"slots":[],"events":[]}},{"name":"NuxtLogo","path":"components/content/FrameworkList/NuxtLogo.vue","meta":{"props":[],"slots":[],"events":[]}},{"name":"VueLogo","path":"components/content/FrameworkList/VueLogo.vue","meta":{"props":[],"slots":[],"events":[]}},{"name":"Code","path":"components/content/common/Code.vue","meta":{"props":[],"slots":[],"events":[]}},{"name":"Showcase","path":"components/content/common/Showcase.vue","meta":{"props":[],"slots":[],"events":[]}},{"name":"Stack","path":"components/content/common/Stack.vue","meta":{"props":[],"slots":[],"events":[]}},{"name":"Wrap","path":"components/content/common/Wrap.vue","meta":{"props":[],"slots":[],"events":[]}},{"name":"ExpandedStyle","path":"components/content/examples/accordion/ExpandedStyle.vue","meta":{"props":[],"slots":[],"events":[]}},{"name":"SimpleAccordion","path":"components/content/examples/accordion/SimpleAccordion.vue","meta":{"props":[],"slots":[],"events":[]}},{"name":"AccentAlert","path":"components/content/examples/alert/AccentAlert.vue","meta":{"props":[],"slots":[],"events":[]}},{"name":"Alert","path":"components/content/examples/alert/Alert.vue","meta":{"props":[],"slots":[],"events":[]}},{"name":"BaseAlert","path":"components/content/examples/alert/BaseAlert.vue","meta":{"props":[],"slots":[],"events":[]}},{"name":"Composition","path":"components/content/examples/alert/Composition.vue","meta":{"props":[],"slots":[],"events":[]}},{"name":"CompositionExample2","path":"components/content/examples/alert/CompositionExample2.vue","meta":{"props":[],"slots":[],"events":[]}},{"name":"IconAlert","path":"components/content/examples/alert/IconAlert.vue","meta":{"props":[],"slots":[],"events":[]}},{"name":"StatusAlert","path":"components/content/examples/alert/StatusAlert.vue","meta":{"props":[],"slots":[],"events":[]}},{"name":"AspectRatioEImage","path":"components/content/examples/aspectratio/AspectRatioEImage.vue","meta":{"props":[],"slots":[],"events":[]}},{"name":"AspectRatioEMap","path":"components/content/examples/aspectratio/AspectRatioEMap.vue","meta":{"props":[],"slots":[],"events":[]}},{"name":"AspectRatioEVideo","path":"components/content/examples/aspectratio/AspectRatioEVideo.vue","meta":{"props":[],"slots":[],"events":[]}},{"name":"Avatar","path":"components/content/examples/avatar/Avatar.vue","meta":{"props":[],"slots":[],"events":[]}},{"name":"AvatarBadge","path":"components/content/examples/avatar/AvatarBadge.vue","meta":{"props":[],"slots":[],"events":[]}},{"name":"AvatarGroup","path":"components/content/examples/avatar/AvatarGroup.vue","meta":{"props":[],"slots":[],"events":[]}},{"name":"BaseBadge","path":"components/content/examples/badge/BaseBadge.vue","meta":{"props":[],"slots":[],"events":[]}},{"name":"ColorBadge","path":"components/content/examples/badge/ColorBadge.vue","meta":{"props":[],"slots":[],"events":[]}},{"name":"CompositionBadge","path":"components/content/examples/badge/CompositionBadge.vue","meta":{"props":[],"slots":[],"events":[]}},{"name":"CompositionBadgeTwo","path":"components/content/examples/badge/CompositionBadgeTwo.vue","meta":{"props":[],"slots":[],"events":[]}},{"name":"VariantBadge","path":"components/content/examples/badge/VariantBadge.vue","meta":{"props":[],"slots":[],"events":[]}},{"name":"BreadcrumbComposition","path":"components/content/examples/breadcrumb/BreadcrumbComposition.vue","meta":{"props":[],"slots":[],"events":[]}},{"name":"DefaultSeparator","path":"components/content/examples/breadcrumb/DefaultSeparator.vue","meta":{"props":[],"slots":[],"events":[]}},{"name":"FunctionalSeparator","path":"components/content/examples/breadcrumb/FunctionalSeparator.vue","meta":{"props":[],"slots":[],"events":[]}},{"name":"SimpleBreadcrumb","path":"components/content/examples/breadcrumb/SimpleBreadcrumb.vue","meta":{"props":[],"slots":[],"events":[]}},{"name":"SlotSeparator","path":"components/content/examples/breadcrumb/SlotSeparator.vue","meta":{"props":[],"slots":[],"events":[]}},{"name":"StringSeparator","path":"components/content/examples/breadcrumb/StringSeparator.vue","meta":{"props":[],"slots":[],"events":[]}},{"name":"BaseButton","path":"components/content/examples/button/BaseButton.vue","meta":{"props":[],"slots":[],"events":[]}},{"name":"ButtonComposition","path":"components/content/examples/button/ButtonComposition.vue","meta":{"props":[],"slots":[],"events":[]}},{"name":"ButtonGroup","path":"components/content/examples/button/ButtonGroup.vue","meta":{"props":[],"slots":[],"events":[]}},{"name":"CustomButton","path":"components/content/examples/button/CustomButton.vue","meta":{"props":[],"slots":[],"events":[]}},{"name":"IconButton","path":"components/content/examples/button/IconButton.vue","meta":{"props":[],"slots":[],"events":[]}},{"name":"LoadingButton","path":"components/content/examples/button/LoadingButton.vue","meta":{"props":[],"slots":[],"events":[]}},{"name":"SizesButton","path":"components/content/examples/button/SizesButton.vue","meta":{"props":[],"slots":[],"events":[]}},{"name":"VariantButton","path":"components/content/examples/button/VariantButton.vue","meta":{"props":[],"slots":[],"events":[]}},{"name":"IconCenter","path":"components/content/examples/center/IconCenter.vue","meta":{"props":[],"slots":[],"events":[]}},{"name":"SimpleCenter","path":"components/content/examples/center/SimpleCenter.vue","meta":{"props":[],"slots":[],"events":[]}},{"name":"SquareAndCircle","path":"components/content/examples/center/SquareAndCircle.vue","meta":{"props":[],"slots":[],"events":[]}},{"name":"Checkbox","path":"components/content/examples/checkbox/Checkbox.vue","meta":{"props":[],"slots":[],"events":[]}},{"name":"CheckboxGroup","path":"components/content/examples/checkbox/CheckboxGroup.vue","meta":{"props":[],"slots":[],"events":[]}},{"name":"ColorsCheckbox","path":"components/content/examples/checkbox/ColorsCheckbox.vue","meta":{"props":[],"slots":[],"events":[]}},{"name":"DisabledCheckbox","path":"components/content/examples/checkbox/DisabledCheckbox.vue","meta":{"props":[],"slots":[],"events":[]}},{"name":"Indeterminate","path":"components/content/examples/checkbox/Indeterminate.vue","meta":{"props":[],"slots":[],"events":[]}},{"name":"SizesCheckbox","path":"components/content/examples/checkbox/SizesCheckbox.vue","meta":{"props":[],"slots":[],"events":[]}},{"name":"CloseButton","path":"components/content/examples/closebutton/CloseButton.vue","meta":{"props":[],"slots":[],"events":[]}},{"name":"CloseButtonSizes","path":"components/content/examples/closebutton/CloseButtonSizes.vue","meta":{"props":[],"slots":[],"events":[]}},{"name":"ColorsCode","path":"components/content/examples/code/ColorsCode.vue","meta":{"props":[],"slots":[],"events":[]}},{"name":"SimpleCode","path":"components/content/examples/code/SimpleCode.vue","meta":{"props":[],"slots":[],"events":[]}},{"name":"VariantCode","path":"components/content/examples/code/VariantCode.vue","meta":{"props":[],"slots":[],"events":[]}},{"name":"HeightCollapse","path":"components/content/examples/collapse/HeightCollapse.vue","meta":{"props":[],"slots":[],"events":[]}},{"name":"SimpleCollapse","path":"components/content/examples/collapse/SimpleCollapse.vue","meta":{"props":[],"slots":[],"events":[]}},{"name":"CompareFlex","path":"components/content/examples/flex/CompareFlex.vue","meta":{"props":[],"slots":[],"events":[]}},{"name":"SignUpFlex","path":"components/content/examples/flex/SignUpFlex.vue","meta":{"props":[],"slots":[],"events":[]}},{"name":"SimpleFlex","path":"components/content/examples/flex/SimpleFlex.vue","meta":{"props":[],"slots":[],"events":[]}},{"name":"SpacerFlex","path":"components/content/examples/flex/SpacerFlex.vue","meta":{"props":[],"slots":[],"events":[]}},{"name":"BasicHeading","path":"components/content/examples/heading/BasicHeading.vue","meta":{"props":[],"slots":[],"events":[]}},{"name":"CompositionHeading","path":"components/content/examples/heading/CompositionHeading.vue","meta":{"props":[],"slots":[],"events":[]}},{"name":"OverrideHeading","path":"components/content/examples/heading/OverrideHeading.vue","meta":{"props":[],"slots":[],"events":[]}},{"name":"SizesHeading","path":"components/content/examples/heading/SizesHeading.vue","meta":{"props":[],"slots":[],"events":[]}},{"name":"TruncatedHeading","path":"components/content/examples/heading/TruncatedHeading.vue","meta":{"props":[],"slots":[],"events":[]}},{"name":"Icon","path":"components/content/examples/icons/Icon.vue","meta":{"props":[],"slots":[],"events":[]}},{"name":"BoxImage","path":"components/content/examples/image/BoxImage.vue","meta":{"props":[],"slots":[],"events":[]}},{"name":"FallbackImage","path":"components/content/examples/image/FallbackImage.vue","meta":{"props":[],"slots":[],"events":[]}},{"name":"RoundedImage","path":"components/content/examples/image/RoundedImage.vue","meta":{"props":[],"slots":[],"events":[]}},{"name":"SimpleImage","path":"components/content/examples/image/SimpleImage.vue","meta":{"props":[],"slots":[],"events":[]}},{"name":"BasicInput","path":"components/content/examples/input/BasicInput.vue","meta":{"props":[],"slots":[],"events":[]}},{"name":"InputAddon","path":"components/content/examples/input/InputAddon.vue","meta":{"props":[],"slots":[],"events":[]}},{"name":"InputAppearance","path":"components/content/examples/input/InputAppearance.vue","meta":{"props":[],"slots":[],"events":[]}},{"name":"InputDate","path":"components/content/examples/input/InputDate.vue","meta":{"props":[],"slots":[],"events":[]}},{"name":"InputElements","path":"components/content/examples/input/InputElements.vue","meta":{"props":[],"slots":[],"events":[]}},{"name":"InputFocus","path":"components/content/examples/input/InputFocus.vue","meta":{"props":[],"slots":[],"events":[]}},{"name":"InputHtmlSize","path":"components/content/examples/input/InputHtmlSize.vue","meta":{"props":[],"slots":[],"events":[]}},{"name":"InputPassword","path":"components/content/examples/input/InputPassword.vue","meta":{"props":[],"slots":[],"events":[]}},{"name":"InputPlaceholderStyle","path":"components/content/examples/input/InputPlaceholderStyle.vue","meta":{"props":[],"slots":[],"events":[]}},{"name":"SizeInput","path":"components/content/examples/input/SizeInput.vue","meta":{"props":[],"slots":[],"events":[]}},{"name":"SimpleGridAutoResponsive","path":"components/content/examples/simplegrid/SimpleGridAutoResponsive.vue","meta":{"props":[],"slots":[],"events":[]}},{"name":"SimpleGridExample","path":"components/content/examples/simplegrid/SimpleGridExample.vue","meta":{"props":[],"slots":[],"events":[]}},{"name":"SimpleGridResponsive","path":"components/content/examples/simplegrid/SimpleGridResponsive.vue","meta":{"props":[],"slots":[],"events":[]}},{"name":"SimpleGridSpacing","path":"components/content/examples/simplegrid/SimpleGridSpacing.vue","meta":{"props":[],"slots":[],"events":[]}},{"name":"BasicStack","path":"components/content/examples/stack/BasicStack.vue","meta":{"props":[],"slots":[],"events":[]}},{"name":"HorizontalStack","path":"components/content/examples/stack/HorizontalStack.vue","meta":{"props":[],"slots":[],"events":[]}},{"name":"HorizontalStackTwo","path":"components/content/examples/stack/HorizontalStackTwo.vue","meta":{"props":[],"slots":[],"events":[]}},{"name":"HtmlStack","path":"components/content/examples/stack/HtmlStack.vue","meta":{"props":[],"slots":[],"events":[]}},{"name":"ReverseStack","path":"components/content/examples/stack/ReverseStack.vue","meta":{"props":[],"slots":[],"events":[]}},{"name":"ColoredTabs","path":"components/content/examples/tabs/ColoredTabs.vue","meta":{"props":[],"slots":[],"events":[]}},{"name":"FittedTabs","path":"components/content/examples/tabs/FittedTabs.vue","meta":{"props":[],"slots":[],"events":[]}},{"name":"SimpleTabs","path":"components/content/examples/tabs/SimpleTabs.vue","meta":{"props":[],"slots":[],"events":[]}},{"name":"SizesTabs","path":"components/content/examples/tabs/SizesTabs.vue","meta":{"props":[],"slots":[],"events":[]}},{"name":"VariantTabs","path":"components/content/examples/tabs/VariantTabs.vue","meta":{"props":[],"slots":[],"events":[]}},{"name":"Tag","path":"components/content/examples/tag/Tag.vue","meta":{"props":[],"slots":[],"events":[]}},{"name":"TagCloseButton","path":"components/content/examples/tag/TagCloseButton.vue","meta":{"props":[],"slots":[],"events":[]}},{"name":"TagLabel","path":"components/content/examples/tag/TagLabel.vue","meta":{"props":[],"slots":[],"events":[]}},{"name":"TagLeftIcon","path":"components/content/examples/tag/TagLeftIcon.vue","meta":{"props":[],"slots":[],"events":[]}},{"name":"TagRightIcon","path":"components/content/examples/tag/TagRightIcon.vue","meta":{"props":[],"slots":[],"events":[]}},{"name":"AlignWrap","path":"components/content/examples/wrap/AlignWrap.vue","meta":{"props":[],"slots":[],"events":[]}},{"name":"JustifyWrap","path":"components/content/examples/wrap/JustifyWrap.vue","meta":{"props":[],"slots":[],"events":[]}},{"name":"SimpleWrap","path":"components/content/examples/wrap/SimpleWrap.vue","meta":{"props":[],"slots":[],"events":[]}},{"name":"SpacingWrap","path":"components/content/examples/wrap/SpacingWrap.vue","meta":{"props":[],"slots":[],"events":[]}}]}